sqlalchemy_dm/__init__.py
sqlalchemy_dm/base.py
sqlalchemy_dm/dmPython.py
sqlalchemy_dm/types.py
sqlalchemy_dm_bzx-1.0.0.0.dist-info/LICENSE
sqlalchemy_dm_bzx-1.0.0.0.dist-info/METADATA
sqlalchemy_dm_bzx-1.0.0.0.dist-info/WHEEL
sqlalchemy_dm_bzx-1.0.0.0.dist-info/entry_points.txt
sqlalchemy_dm_bzx-1.0.0.0.dist-info/top_level.txt
sqlalchemy_dm_bzx-1.0.0.0.dist-info/RECORD
