Metadata-Version: 2.1
Name: sqlalchemy-dm-bzx
Version: 1.0.0.0
Summary: SQLAlchemy dialect for DM
Author: Dameng
Author-email: 
License-File: LICENSE
Requires-Dist: dmPython
Requires-Dist: sqlalchemy
